eveline/__init__.py
eveline-0.1.0.dist-info/WHEEL
eveline-0.1.0.dist-info/METADATA
eveline-0.1.0.dist-info/RECORD
