Metadata-Version: 2.1
Name: eveline
Version: 0.1.0
Summary: Placeholder for eveline protocol
License: Proprietary
Author: Stanislav
Author-email: me@h3xco.de
Requires-Python: >=3.9,<4.0
Classifier: License :: Other/Proprietary License
Classifier: Programming Language :: Python :: 3
Classifier: Programming Language :: Python :: 3.10
Classifier: Programming Language :: Python :: 3.9
Requires-Dist: Jinja2 (>=3.0.3,<4.0.0)
